Metadata-Version: 2.1
Name: hello-world-ocr
Version: 1.0.1
Summary: Hello world test for uploading pypi packages
Home-page: https://github.com/wendell-hom
Author: Wendell Hom
Author-email: email@example.com
License: MIT
Keywords: example project
Platform: UNKNOWN
